zemberek_grpc/__init__.py
zemberek_grpc/language_id_pb2.py
zemberek_grpc/language_id_pb2_grpc.py
zemberek_grpc/morphology_pb2.py
zemberek_grpc/morphology_pb2_grpc.py
zemberek_grpc/normalization_pb2.py
zemberek_grpc/normalization_pb2_grpc.py
zemberek_grpc/preprocess_pb2.py
zemberek_grpc/preprocess_pb2_grpc.py
zemberek_grpc-0.16.1.dist-info/METADATA
zemberek_grpc-0.16.1.dist-info/WHEEL
zemberek_grpc-0.16.1.dist-info/top_level.txt
zemberek_grpc-0.16.1.dist-info/zip-safe
zemberek_grpc-0.16.1.dist-info/RECORD
